LICENSE
README.md
pyproject.toml
setup.cfg
setup.py
lyncs_cppyy/__init__.py
lyncs_cppyy/lib.py
lyncs_cppyy/ll.py
lyncs_cppyy/numpy.py
lyncs_cppyy.egg-info/PKG-INFO
lyncs_cppyy.egg-info/SOURCES.txt
lyncs_cppyy.egg-info/dependency_links.txt
lyncs_cppyy.egg-info/requires.txt
lyncs_cppyy.egg-info/top_level.txt
lyncs_cppyy/include/lyncs_cppyy.h
lyncs_cppyy/include/to_pointers.h
lyncs_cppyy/include/utils.h
test/test_example.py
test/test_lib.py
test/test_ll.py
test/test_numpy.py
test/test_utils.py
test/cnumbers/meson.build
test/cnumbers/numbers.c
test/cnumbers/numbers.h
test/cnumbers/numbers.hpp