Metadata-Version: 2.1
Name: lyncs-cppyy
Version: 0.2.0
Summary: cppyy wrapper for Lyncs
Home-page: https://github.com/Lyncs-API/lyncs.cppyy
Author: Simone Bacchio
Author-email: s.bacchio@gmail.com
License: UNKNOWN
Project-URL: Source, https://github.com/Lyncs-API/lyncs.cppyy
Project-URL: Documentation, https://github.com/Lyncs-API/lyncs.cppyy/README.md
Project-URL: Tracker, https://github.com/Lyncs-API/lyncs.cppyy/issues
Project-URL: Download, https://github.com/Lyncs-API/lyncs.cppyy/archive/master.zip
Keywords: Lyncs,cppyy
Platform: UNKNOWN
Classifier: Intended Audience :: Education
Classifier: Natural Language :: English
Classifier: Topic :: Scientific/Engineering :: Physics
Classifier: License :: OSI Approved :: BSD License
Classifier: Operating System :: Unix
Classifier: Intended Audience :: Developers
Classifier: Intended Audience :: Science/Research
Classifier: Development Status :: 1 - Planning
Classifier: Programming Language :: Python :: 3 :: Only
Provides-Extra: test
Provides-Extra: all
